LibVQ/__init__.py
LibVQ/inference.py
LibVQ/temp_learnable_vq.py
LibVQ/train.py
LibVQ/utils.py
LibVQ/base_index/BaseIndex.py
LibVQ/base_index/FaissIndex.py
LibVQ/base_index/ScannIndex.py
LibVQ/base_index/__init__.py
LibVQ/dataset/__init__.py
LibVQ/dataset/dataset.py
LibVQ/dataset/preprocess.py
LibVQ/learnable_index/__init__.py
LibVQ/learnable_index/learnable_index.py
LibVQ/learnable_index/learnable_index_with_encoder.py
LibVQ/models/__init__.py
LibVQ/models/encoder.py
LibVQ/models/ivf_quantizer.py
LibVQ/models/learnable_vq.py
LibVQ/models/pq_quantizer.py
LibVQ-0.0.2.dist-info/LICENSE
LibVQ-0.0.2.dist-info/METADATA
LibVQ-0.0.2.dist-info/WHEEL
LibVQ-0.0.2.dist-info/top_level.txt
LibVQ-0.0.2.dist-info/RECORD
