Metadata-Version: 2.1
Name: LibVQ
Version: 0.0.2
Summary: A Library For Dense Retrieval Oriented Vector Quantization
Home-page: https://github.com/staoxiao/LibVQ
Author: Shitao Xiao, Zheng Liu, Yingxia Shao
Author-email: stxiao@bupt.edu.cn
License: MIT License
Keywords: Vector Quantization,ANN,IVF
Platform: UNKNOWN
Requires-Dist: transformers (>=4.9.0)
Requires-Dist: faiss-gpu (==1.6.4.post2)
Requires-Dist: scann (==1.2.3)
Requires-Dist: tqdm
Requires-Dist: torch (>=1.6.0)
Requires-Dist: numpy
